moneypandas/__init__.py
moneypandas/_accessor.py
moneypandas/base.py
moneypandas/dtypes.py
moneypandas/money_array.py
moneypandas/parser.py
tests/__init__.py
tests/test_dtypes.py
tests/test_interface.py
tests/test_ip.py
tests/test_money_pandas.py
tests/test_pandas_methods.py
tests/test_parser.py
moneypandas-0.9.5.dist-info/LICENSE
moneypandas-0.9.5.dist-info/METADATA
moneypandas-0.9.5.dist-info/WHEEL
moneypandas-0.9.5.dist-info/top_level.txt
moneypandas-0.9.5.dist-info/RECORD
