Metadata-Version: 2.1
Name: moneypandas
Version: 0.9.5
Summary: Money type for pandas
Home-page: https://github.com/flaxandteal/moneypandas
Author: Phil Weir (moneypandas tweaks), Tom Augspurger (cyberpandas)
Author-email: phil.weir@flaxandteal.co.uk
License: BSD
Platform: UNKNOWN
Classifier: License :: OSI Approved :: BSD License
Classifier: Programming Language :: Python :: 3
Classifier: Programming Language :: Python :: 3.5
Classifier: Programming Language :: Python :: 3.6
Requires-Dist: iso4217parse
Requires-Dist: money
Requires-Dist: numpy
Requires-Dist: pandas
Requires-Dist: six
